Pydeconz/BaseElement.py
Pydeconz/Config.py
Pydeconz/Group.py
Pydeconz/Light.py
Pydeconz/Router.py
Pydeconz/Rule.py
Pydeconz/Sensor.py
Pydeconz/__init__.py
Pydeconz/rules.py
deconzpy/BaseElement.py
deconzpy/Config.py
deconzpy/Group.py
deconzpy/Light.py
deconzpy/Router.py
deconzpy/Rule.py
deconzpy/Sensor.py
deconzpy/__init__.py
deconzpy-0.9.0.dist-info/LICENSE
deconzpy-0.9.0.dist-info/METADATA
deconzpy-0.9.0.dist-info/WHEEL
deconzpy-0.9.0.dist-info/top_level.txt
deconzpy-0.9.0.dist-info/RECORD
