Metadata-Version: 2.1
Name: deconzpy
Version: 0.9.0
Summary: UNKNOWN
Home-page: https://github.com/balu-/deconzpy
Author: balu-
License: UNKNOWN
Keywords: deconz zigbee homeautomation
Platform: UNKNOWN
Classifier: Development Status :: 4 - Beta
Classifier: License :: OSI Approved :: MIT License
Classifier: Programming Language :: Python :: 3.5
Requires-Dist: requests
Requires-Dist: websocket-client
